herder/__init__.py
herder/main.py
herder/utils/__init__.py
herder/utils/input.py
herder/utils/llm.py
herder_cli-0.1.4.dist-info/licenses/LICENSE
herder_cli-0.1.4.dist-info/METADATA
herder_cli-0.1.4.dist-info/WHEEL
herder_cli-0.1.4.dist-info/entry_points.txt
herder_cli-0.1.4.dist-info/top_level.txt
herder_cli-0.1.4.dist-info/RECORD
