Metadata-Version: 2.4
Name: herder-cli
Version: 0.1.4
Summary: Add your description here
Requires-Python: >=3.13
License-File: LICENSE
Requires-Dist: mcp>=1.12.3
Requires-Dist: mcpadapt>=0.1.12
Requires-Dist: ollama>=0.5.1
Requires-Dist: prompt-toolkit>=3.0.51
Requires-Dist: pyfiglet>=1.0.3
Requires-Dist: smolagents>=1.20.0
Dynamic: license-file
